zmcat-0.0.11.dist-info/RECORD
zmcat-0.0.11.dist-info/entry_points.txt
zmcat-0.0.11.dist-info/DESCRIPTION.rst
zmcat-0.0.11.dist-info/top_level.txt
zmcat-0.0.11.dist-info/WHEEL
zmcat-0.0.11.dist-info/METADATA
zmcat-0.0.11.dist-info/metadata.json
zmcat/tool.py
zmcat/__init__.py
