Metadata-Version: 2.0
Name: zmcat
Version: 0.0.11
Summary: A simple command line tool to test ZMQ push/pull/pub/sub sockets. Based on https://github.com/lucasdicioccio/zmcat
Home-page: https://github.com/flyte/zmcat
Author: Ellis Percival
Author-email: zmcat@failcode.co.uk
License: UNLICENSE
Keywords: zmq zeromq netcat nc 0mq
Platform: UNKNOWN
Requires-Dist: pyzmq
Requires-Dist: argparse
